Metadata-Version: 2.4
Name: hpsv3
Version: 1.0.0
Summary: HPSv3: Towards Wide-Spectrum Human Preference Score - A VLM-based preference model for image quality assessment
Author: Yunhao Shui, Yuhang Ma
License: MIT
Project-URL: Homepage, https://mizzenai.github.io/HPSv3/
Project-URL: Source, https://github.com/MizzenAI/HPSv3
Project-URL: Documentation, https://github.com/MizzenAI/HPSv3/blob/main/README.md
Project-URL: Paper, https://arxiv.org/abs/2411.07232
Keywords: machine learning,computer vision,human preference,image quality,VLM,multimodal
Classifier: Development Status :: 4 - Beta
Classifier: Intended Audience :: Developers
Classifier: Intended Audience :: Science/Research
Classifier: License :: OSI Approved :: MIT License
Classifier: Operating System :: OS Independent
Classifier: Programming Language :: Python :: 3
Classifier: Programming Language :: Python :: 3.8
Classifier: Programming Language :: Python :: 3.9
Classifier: Programming Language :: Python :: 3.10
Classifier: Programming Language :: Python :: 3.11
Classifier: Topic :: Scientific/Engineering :: Artificial Intelligence
Classifier: Topic :: Software Development :: Libraries :: Python Modules
Requires-Python: >=3.8
License-File: LICENSE
Requires-Dist: torch>=2.0.0
Requires-Dist: torchvision>=0.15.0
Requires-Dist: transformers==4.45.2
Requires-Dist: accelerate>=0.20.0
Requires-Dist: datasets>=2.10.0
Requires-Dist: diffusers>=0.20.0
Requires-Dist: Pillow>=9.0.0
Requires-Dist: numpy>=1.20.0
Requires-Dist: tqdm>=4.60.0
Requires-Dist: pyyaml>=6.0
Requires-Dist: omegaconf>=2.3.0
Requires-Dist: opencv-python>=4.5.0
Requires-Dist: safetensors>=0.3.0
Requires-Dist: einops>=0.6.0
Requires-Dist: qwen-vl-utils>=0.0.8
Requires-Dist: timm>=0.9.0
Requires-Dist: deepspeed>=0.12.0
Requires-Dist: peft>=0.8.0
Requires-Dist: trl>=0.7.0
Requires-Dist: fire>=0.7.0
Dynamic: license-file
